torch_mlir_gml.libs/libTorchMLIRAggregateCAPI-90046011.so
torch_mlir_e2e_test/utils.py
torch_mlir_e2e_test/reporting.py
torch_mlir_e2e_test/framework.py
torch_mlir_e2e_test/annotations.py
torch_mlir_e2e_test/__init__.py
torch_mlir_e2e_test/registry.py
torch_mlir_e2e_test/test_suite/return_types.py
torch_mlir_e2e_test/test_suite/scalar.py
torch_mlir_e2e_test/test_suite/pooling.py
torch_mlir_e2e_test/test_suite/scalar_comparison.py
torch_mlir_e2e_test/test_suite/reduction.py
torch_mlir_e2e_test/test_suite/mlp.py
torch_mlir_e2e_test/test_suite/conv.py
torch_mlir_e2e_test/test_suite/elementwise_comparison.py
torch_mlir_e2e_test/test_suite/type_promotion.py
torch_mlir_e2e_test/test_suite/cast.py
torch_mlir_e2e_test/test_suite/stats.py
torch_mlir_e2e_test/test_suite/backprop.py
torch_mlir_e2e_test/test_suite/norm_like.py
torch_mlir_e2e_test/test_suite/squeeze.py
torch_mlir_e2e_test/test_suite/rng.py
torch_mlir_e2e_test/test_suite/constant_alloc.py
torch_mlir_e2e_test/test_suite/basic.py
torch_mlir_e2e_test/test_suite/quantized_models.py
torch_mlir_e2e_test/test_suite/type_conversion.py
torch_mlir_e2e_test/test_suite/vision_models.py
torch_mlir_e2e_test/test_suite/arange.py
torch_mlir_e2e_test/test_suite/nll_loss.py
torch_mlir_e2e_test/test_suite/argmax.py
torch_mlir_e2e_test/test_suite/__init__.py
torch_mlir_e2e_test/test_suite/custom_op_example.py
torch_mlir_e2e_test/test_suite/scatter.py
torch_mlir_e2e_test/test_suite/slice_like.py
torch_mlir_e2e_test/test_suite/index_select.py
torch_mlir_e2e_test/test_suite/histogram_binning_calibration.py
torch_mlir_e2e_test/test_suite/matmul.py
torch_mlir_e2e_test/test_suite/control_flow.py
torch_mlir_e2e_test/test_suite/elementwise.py
torch_mlir_e2e_test/test_suite/reshape_like.py
torch_mlir_e2e_test/test_suite/threshold.py
torch_mlir_e2e_test/stablehlo_backends/linalg_on_tensors.py
torch_mlir_e2e_test/stablehlo_backends/abc.py
torch_mlir_e2e_test/stablehlo_backends/__init__.py
torch_mlir_gml-2.1.2.dist-info/LICENSE
torch_mlir_gml-2.1.2.dist-info/RECORD
torch_mlir_gml-2.1.2.dist-info/METADATA
torch_mlir_gml-2.1.2.dist-info/dependency_links.txt
torch_mlir_gml-2.1.2.dist-info/WHEEL
torch_mlir_gml-2.1.2.dist-info/top_level.txt
