Metadata-Version: 2.1
Name: torch-mlir-gml
Version: 2.1.2
Summary: First-class interop between PyTorch and MLIR
Author: Sean Silva
Author-email: silvasean@google.com
License-File: LICENSE
Requires-Dist: numpy
Requires-Dist: packaging
Requires-Dist: torch ==2.1.*
